catocli/__init__.py
catocli/__main__.py
catocli/clisettings.json
catocli/post_install.py
catocli/Utils/clidriver.py
catocli/Utils/cliutils.py
catocli/Utils/formatter_account_metrics.py
catocli/Utils/formatter_app_stats.py
catocli/Utils/formatter_app_stats_timeseries.py
catocli/Utils/formatter_events_timeseries.py
catocli/Utils/formatter_licensing.py
catocli/Utils/formatter_pop_locations.py
catocli/Utils/formatter_socket_port_metrics.py
catocli/Utils/formatter_socket_port_metrics_timeseries.py
catocli/Utils/formatter_utils.py
catocli/Utils/graphql_utils.py
catocli/Utils/help_formatter.py
catocli/Utils/profile_manager.py
catocli/Utils/version_checker.py
catocli/parsers/customParserApiClient.py
catocli/parsers/configure/__init__.py
catocli/parsers/configure/configure.py
catocli/parsers/custom/README.md
catocli/parsers/custom/__init__.py
catocli/parsers/custom/customLib.py
catocli/parsers/custom/eventsFeedEnhanced.py
catocli/parsers/custom/export_rules/__init__.py
catocli/parsers/custom/export_rules/export_rules.py
catocli/parsers/custom/export_sites/__init__.py
catocli/parsers/custom/export_sites/export_sites.py
catocli/parsers/custom/import_rules_to_tf/__init__.py
catocli/parsers/custom/import_rules_to_tf/import_rules_to_tf.py
catocli/parsers/custom/import_sites_to_tf/__init__.py
catocli/parsers/custom/import_sites_to_tf/import_sites_to_tf.py
catocli/parsers/custom/import_validate_site_location/__init__.py
catocli/parsers/custom/import_validate_site_location/validate_site_location.py
catocli/parsers/custom/query_appCategory/README.md
catocli/parsers/custom/query_appCategory/__init__.py
catocli/parsers/custom/query_appCategory/query.appCategory.json
catocli/parsers/custom/query_eventsFeed/README.md
catocli/parsers/custom/query_eventsFeed/__init__.py
catocli/parsers/custom/query_siteLocation/README.md
catocli/parsers/custom/query_siteLocation/__init__.py
catocli/parsers/custom/query_siteLocation/query.siteLocation.json
catocli/parsers/custom/scim/README.md
catocli-3.0.59.dist-info/licenses/LICENSE
catocli-3.0.59.dist-info/METADATA
catocli-3.0.59.dist-info/WHEEL
catocli-3.0.59.dist-info/entry_points.txt
catocli-3.0.59.dist-info/top_level.txt
catocli-3.0.59.dist-info/RECORD
